marketforge/__init__.py
marketforge/__main__.py
marketforge/aggregation/__init__.py
marketforge/aggregation/timeframes.py
marketforge/cli/__init__.py
marketforge/cli/parser.py
marketforge/cli/runner.py
marketforge/config/__init__.py
marketforge/config/defaults.py
marketforge/config/settings.py
marketforge/configs/__init__.py
marketforge/configs/base.py
marketforge/configs/crypto_config.py
marketforge/configs/forex_config.py
marketforge/configs/loader.py
marketforge/configs/stocks_config.py
marketforge/core/__init__.py
marketforge/core/correlation.py
marketforge/core/garch.py
marketforge/core/regimes.py
marketforge/core/returns.py
marketforge/generators/__init__.py
marketforge/generators/anomalies.py
marketforge/generators/ohlcv.py
marketforge/generators/volume.py
marketforge/markets/__init__.py
marketforge/markets/base.py
marketforge/markets/crypto.py
marketforge/markets/forex.py
marketforge/markets/stocks.py
marketforge/output/__init__.py
marketforge/output/csv_writer.py
marketforge/processing/__init__.py
marketforge/processing/batch.py
marketforge/utils/__init__.py
marketforge/utils/random.py
marketforge/utils/time.py
marketforge-1.0.0.dist-info/licenses/LICENSE
marketforge-1.0.0.dist-info/licenses/NOTICE
marketforge-1.0.0.dist-info/METADATA
marketforge-1.0.0.dist-info/WHEEL
marketforge-1.0.0.dist-info/entry_points.txt
marketforge-1.0.0.dist-info/top_level.txt
marketforge-1.0.0.dist-info/RECORD
