Metadata-Version: 2.4
Name: marketforge
Version: 1.0.0
Summary: A professional-grade synthetic OHLCV data generator
Home-page: https://github.com/DamienReichhart/MarketForge
Author: REICHHART Damien
License: AGPL-3.0
Project-URL: Homepage, https://github.com/DamienReichhart/MarketForge
Project-URL: Documentation, https://github.com/DamienReichhart/MarketForge
Project-URL: Repository, https://github.com/DamienReichhart/MarketForge
Classifier: Development Status :: 4 - Beta
Classifier: Intended Audience :: Developers
Classifier: Intended Audience :: Financial and Insurance Industry
Classifier: License :: OSI Approved :: GNU Affero General Public License v3
Classifier: Operating System :: OS Independent
Classifier: Programming Language :: Python :: 3
Classifier: Programming Language :: Python :: 3.10
Classifier: Programming Language :: Python :: 3.11
Classifier: Programming Language :: Python :: 3.12
Classifier: Topic :: Office/Business :: Financial :: Investment
Classifier: Topic :: Scientific/Engineering :: Artificial Intelligence
Requires-Python: >=3.10
License-File: LICENSE
License-File: NOTICE
Requires-Dist: numpy>=2.4.0
Requires-Dist: scipy>=1.16.3
Requires-Dist: pandas>=2.3.3
Requires-Dist: click>=8.3.1
Requires-Dist: tqdm>=4.67.1
Provides-Extra: dev
Requires-Dist: mypy>=1.19.1; extra == "dev"
Dynamic: home-page
Dynamic: license-file
Dynamic: requires-python
